{"filename":"uploads/db.json","collections":[{"name":"list","data":[{"fieldname":"file","originalname":"SQL_Homework1.txt","encoding":"7bit","mimetype":"text/plain","destination":"uploads/","filename":"42bc94684802edd55b0fc4bc561f3395","path":"uploads\\42bc94684802edd55b0fc4bc561f3395","size":459,"meta":{"revision":0,"created":1508438770014,"version":0},"$loki":1}],"idIndex":[1],"binaryIndices":{},"constraints":null,"uniqueNames":[],"transforms":{},"objType":"list","dirty":true,"cachedIndex":null,"cachedBinaryIndex":null,"cachedData":null,"adaptiveBinaryIndices":true,"transactional":false,"cloneObjects":false,"cloneMethod":"parse-stringify","asyncListeners":false,"disableChangesApi":true,"disableDeltaChangesApi":true,"autoupdate":false,"serializableIndices":true,"ttl":null,"maxId":1,"DynamicViews":[],"events":{"insert":[null],"update":[null],"pre-insert":[],"pre-update":[],"close":[],"flushbuffer":[],"error":[],"delete":[null],"warning":[null]},"changes":[]}],"databaseVersion":1.5,"engineVersion":1.5,"autosave":false,"autosaveInterval":5000,"autosaveHandle":null,"throttledSaves":true,"options":{"persistenceMethod":"fs","serializationMethod":"normal","destructureDelimiter":"$<\n"},"persistenceMethod":"fs","persistenceAdapter":null,"verbose":false,"events":{"init":[null],"loaded":[],"flushChanges":[],"close":[],"changes":[],"warning":[]},"ENV":"NODEJS"}